mlworkflow/__init__.py
mlworkflow/clean_ipynb.py
mlworkflow/dashboard.py
mlworkflow/data_collection.py
mlworkflow/datasets.py
mlworkflow/environment.py
mlworkflow/interactive.py
mlworkflow/keras_utils.py
mlworkflow/notebook.py
mlworkflow/tf_utils.py
mlworkflow/transforms.py
mlworkflow/utils.py
mlworkflow-0.0.5.dist-info/METADATA
mlworkflow-0.0.5.dist-info/RECORD
mlworkflow-0.0.5.dist-info/WHEEL
mlworkflow-0.0.5.dist-info/top_level.txt
