Metadata-Version: 2.1
Name: mlworkflow
Version: 0.0.5
Summary: A workflow-improving library for manipulating ML experiments
Home-page: https://github.com/mistasse/mlworkflow
Author: Maxime Istasse
Author-email: istassem@gmail.com
License: MIT
Platform: UNKNOWN
Requires-Python: >=3.6
Requires-Dist: numpy
Requires-Dist: tqdm
Requires-Dist: ipywidgets
